iflow_mcp_mcp_music_analysis-0.1.42.dist-info/licenses/LICENSE
mcp_music_analysis/__init__.py
mcp_music_analysis/server.py
iflow_mcp_mcp_music_analysis-0.1.42.dist-info/METADATA
iflow_mcp_mcp_music_analysis-0.1.42.dist-info/WHEEL
iflow_mcp_mcp_music_analysis-0.1.42.dist-info/entry_points.txt
iflow_mcp_mcp_music_analysis-0.1.42.dist-info/top_level.txt
iflow_mcp_mcp_music_analysis-0.1.42.dist-info/RECORD
