Metadata-Version: 2.4
Name: iflow-mcp_mcp-music-analysis
Version: 0.1.42
Summary: \A MCP server with music tools\
Author-email: hugohow <hugohowchoong@gmail.com>
Project-URL: Homepage, https://github.com/hugohow/mcp-music-analysis
Project-URL: Repository, https://github.com/hugohow/mcp-music-analysis
Project-URL: Documentation, https://github.com/hugohow/mcp-music-analysis
Project-URL: Bug Tracker, https://github.com/hugohow/mcp-music-analysis/issues
Requires-Python: >=3.11.11
License-File: LICENSE
Requires-Dist: fastmcp==0.4.1
Requires-Dist: librosa>=0.9.2
Requires-Dist: matplotlib>=3.5.1
Requires-Dist: numpy>=1.21.0
Requires-Dist: pytubefix==8.12.2
Requires-Dist: asyncio>=3.4.3
Requires-Dist: soundfile==0.13.1
Dynamic: license-file
